hello_labdata_rd/__init__.py
hello_labdata_rd/_modidx.py
hello_labdata_rd/core.py
hello_labdata_rd/greetings.py
hello_labdata_rd-0.0.1.dist-info/LICENSE
hello_labdata_rd-0.0.1.dist-info/METADATA
hello_labdata_rd-0.0.1.dist-info/WHEEL
hello_labdata_rd-0.0.1.dist-info/entry_points.txt
hello_labdata_rd-0.0.1.dist-info/top_level.txt
hello_labdata_rd-0.0.1.dist-info/RECORD
